onegov.server-0.9.0-py3.6-nspkg.pth
onegov/server/.gitignore
onegov/server/__init__.py
onegov/server/application.py
onegov/server/cli.py
onegov/server/collection.py
onegov/server/config.py
onegov/server/core.py
onegov/server/errors.py
onegov/server/tracker.py
onegov/server/utils.py
onegov/server/tests/conftest.py
onegov/server/tests/test_cli.py
onegov/server/tests/test_collection.py
onegov/server/tests/test_config.py
onegov/server/tests/test_server.py
onegov/server/tests/test_utils.py
onegov.server-0.9.0.dist-info/METADATA
onegov.server-0.9.0.dist-info/WHEEL
onegov.server-0.9.0.dist-info/entry_points.txt
onegov.server-0.9.0.dist-info/namespace_packages.txt
onegov.server-0.9.0.dist-info/top_level.txt
onegov.server-0.9.0.dist-info/RECORD
