Metadata-Version: 2.1
Name: onegov.server
Version: 0.9.0
Summary: Serves OneGov applications.
Home-page: http://github.com/onegov/onegov.server
Author: Seantis GmbH
Author-email: info@seantis.ch
License: GPLv2
Platform: any
Classifier: Intended Audience :: Developers
Classifier: Programming Language :: Python :: 3 :: Only
Classifier: Programming Language :: Python :: 3.6
Classifier: Programming Language :: Python :: 3.7
Classifier: Topic :: Software Development :: Libraries :: Python Modules
Classifier: License :: OSI Approved :: GNU General Public License v2 (GPLv2)
Requires-Python: >=3.6
Requires-Dist: cached-property
Requires-Dist: click
Requires-Dist: bjoern
Requires-Dist: PyYAML
Requires-Dist: sentry-sdk (<0.11.0,>=0.10.0)
Requires-Dist: watchdog
Requires-Dist: webob
Requires-Dist: xtermcolor
Provides-Extra: test
Requires-Dist: coverage ; extra == 'test'
Requires-Dist: morepath ; extra == 'test'
Requires-Dist: port-for ; extra == 'test'
Requires-Dist: psutil ; extra == 'test'
Requires-Dist: pytest ; extra == 'test'
Requires-Dist: requests ; extra == 'test'
Requires-Dist: webtest ; extra == 'test'
